setup.py
ivi/__init__.py
ivi/cmdline.py
ivi/helpers.py
ivi/optimizations.c
ivi/std_logger.py
ivi/version.py
ivi.egg-info/PKG-INFO
ivi.egg-info/SOURCES.txt
ivi.egg-info/dependency_links.txt
ivi.egg-info/entry_points.txt
ivi.egg-info/not-zip-safe
ivi.egg-info/requires.txt
ivi.egg-info/top_level.txt
ivi/gui/__init__.py
ivi/gui/chromatogramplotter.py
ivi/gui/config.py
ivi/gui/helpers.py
ivi/gui/ivi.py
ivi/gui/ivi_ui.py
ivi/gui/lru_cache.py
ivi/gui/modified_guiqwt.py
ivi/gui/peakmapplotter.py
ivi/gui/plotting_widgets.py
ivi/gui/preferences_dialog.py
ivi/gui/preferences_dialog_ui.py
ivi/gui/spectrumplotter.py
ivi/gui/tree_model.py
ivi/gui/utils.py
ivi/lib/__init__.py
ivi/lib/assign.py
ivi/lib/compress.py
ivi/lib/compress_io_read.py
ivi/lib/compress_io_write.py
ivi/lib/data_structures.py
ivi/lib/id_provider.py
ivi/lib/io.py
ivi/lib/preferences.py