Metadata-Version: 1.0
Name: ivi
Version: 1.0.0
Summary: fast and responsive viewer for peptide identifications from IMSB workflows.
Home-page: UNKNOWN
Author: Uwe Schmitt
Author-email: uwe.schmitt@id.ethz.ch
License: http://opensource.org/licenses/BSD-3-Clause
Platform: any
